dens/__init__.py
dens/admin.py
dens/app_settings.py
dens/apps.py
dens/auth_hooks.py
dens/esi.py
dens/managers.py
dens/models.py
dens/tasks.py
dens/urls.py
dens/views.py
dens/locale/en/LC_MESSAGES/django.mo
dens/locale/en/LC_MESSAGES/django.po
dens/management/commands/dens_debug_assets.py
dens/management/commands/dens_debug_notifications.py
dens/management/commands/dens_update_notifications.py
dens/management/commands/dens_update_owners.py
dens/migrations/0001_initial.py
dens/migrations/0002_alter_mercenarydenreinforcednotification_den.py
dens/migrations/0003_alter_mercenaryden_location.py
dens/migrations/0004_discordwebhook.py
dens/migrations/__init__.py
dens/templates/dens/base.html
dens/templates/dens/dens.html
dens/templates/dens/partials/global_js.html
dens/templates/dens/partials/menu.html
dens/tests/__init__.py
dens/tests/test_den_owners.py
dens/tests/test_dens.py
dens/tests/test_notification.py
dens/tests/test_tasks.py
dens/tests/utils.py
dens/tests/testdata/README.md
dens/tests/testdata/__init__.py
dens/tests/testdata/create_eveuniverse.py
dens/tests/testdata/eveuniverse.json
dens/tests/testdata/load_eveuniverse.py
dens/thirdparty/__init__.py
dens/thirdparty/aadiscordbot.py
dens/thirdparty/charlink_hook.py
dens/thirdparty/structuretimers.py
dens/thirdparty/timerboard.py
aa_dens-1.3.0.dist-info/licenses/LICENSE
aa_dens-1.3.0.dist-info/WHEEL
aa_dens-1.3.0.dist-info/METADATA
aa_dens-1.3.0.dist-info/RECORD
