Metadata-Version: 2.4
Name: aa-dens
Version: 1.3.0
Summary: Mercenary dens plugin app for Alliance Auth.
Author-email: T'rahk Rokym <thrak.rokym@gmail.com>
Requires-Python: >=3.10
Classifier: Environment :: Web Environment
Classifier: Framework :: Django
Classifier: Framework :: Django :: 4.0
Classifier: Framework :: Django :: 4.2
Classifier: Intended Audience :: Developers
Classifier: License :: OSI Approved :: MIT License
Classifier: Operating System :: OS Independent
Classifier: Programming Language :: Python
Classifier: Programming Language :: Python :: 3.10
Classifier: Programming Language :: Python :: 3.11
Classifier: Programming Language :: Python :: 3.12
Classifier: Topic :: Internet :: WWW/HTTP
Classifier: Topic :: Internet :: WWW/HTTP :: Dynamic Content
License-File: LICENSE
Requires-Dist: allianceauth>=4.6
Requires-Dist: django-eveuniverse>=1.5
Requires-Dist: django-datatables-view>=1.20
Requires-Dist: allianceauth-app-utils>=1.25
Requires-Dist: pyyaml>=6.0
Project-URL: Changelog, https://gitlab.com/r0kym/aa-dens/-/blob/master/CHANGELOG.md
Project-URL: Homepage, https://gitlab.com/r0kym/aa-dens
Project-URL: Source, https://gitlab.com/r0kym/aa-dens
Project-URL: Tracker, https://gitlab.com/r0kym/aa-dens/-/issues
